public interface  javassist.bytecode.Opcode extends java.lang.Object
{
    public static final int AALOAD;
    public static final int AASTORE;
    public static final int ACONST_NULL;
    public static final int ALOAD;
    public static final int ALOAD_0;
    public static final int ALOAD_1;
    public static final int ALOAD_2;
    public static final int ALOAD_3;
    public static final int ANEWARRAY;
    public static final int ARETURN;
    public static final int ARRAYLENGTH;
    public static final int ASTORE;
    public static final int ASTORE_0;
    public static final int ASTORE_1;
    public static final int ASTORE_2;
    public static final int ASTORE_3;
    public static final int ATHROW;
    public static final int BALOAD;
    public static final int BASTORE;
    public static final int BIPUSH;
    public static final int CALOAD;
    public static final int CASTORE;
    public static final int CHECKCAST;
    public static final int D2F;
    public static final int D2I;
    public static final int D2L;
    public static final int DADD;
    public static final int DALOAD;
    public static final int DASTORE;
    public static final int DCMPG;
    public static final int DCMPL;
    public static final int DCONST_0;
    public static final int DCONST_1;
    public static final int DDIV;
    public static final int DLOAD;
    public static final int DLOAD_0;
    public static final int DLOAD_1;
    public static final int DLOAD_2;
    public static final int DLOAD_3;
    public static final int DMUL;
    public static final int DNEG;
    public static final int DREM;
    public static final int DRETURN;
    public static final int DSTORE;
    public static final int DSTORE_0;
    public static final int DSTORE_1;
    public static final int DSTORE_2;
    public static final int DSTORE_3;
    public static final int DSUB;
    public static final int DUP;
    public static final int DUP2;
    public static final int DUP2_X1;
    public static final int DUP2_X2;
    public static final int DUP_X1;
    public static final int DUP_X2;
    public static final int F2D;
    public static final int F2I;
    public static final int F2L;
    public static final int FADD;
    public static final int FALOAD;
    public static final int FASTORE;
    public static final int FCMPG;
    public static final int FCMPL;
    public static final int FCONST_0;
    public static final int FCONST_1;
    public static final int FCONST_2;
    public static final int FDIV;
    public static final int FLOAD;
    public static final int FLOAD_0;
    public static final int FLOAD_1;
    public static final int FLOAD_2;
    public static final int FLOAD_3;
    public static final int FMUL;
    public static final int FNEG;
    public static final int FREM;
    public static final int FRETURN;
    public static final int FSTORE;
    public static final int FSTORE_0;
    public static final int FSTORE_1;
    public static final int FSTORE_2;
    public static final int FSTORE_3;
    public static final int FSUB;
    public static final int GETFIELD;
    public static final int GETSTATIC;
    public static final int GOTO;
    public static final int GOTO_W;
    public static final int I2B;
    public static final int I2C;
    public static final int I2D;
    public static final int I2F;
    public static final int I2L;
    public static final int I2S;
    public static final int IADD;
    public static final int IALOAD;
    public static final int IAND;
    public static final int IASTORE;
    public static final int ICONST_0;
    public static final int ICONST_1;
    public static final int ICONST_2;
    public static final int ICONST_3;
    public static final int ICONST_4;
    public static final int ICONST_5;
    public static final int ICONST_M1;
    public static final int IDIV;
    public static final int IFEQ;
    public static final int IFGE;
    public static final int IFGT;
    public static final int IFLE;
    public static final int IFLT;
    public static final int IFNE;
    public static final int IFNONNULL;
    public static final int IFNULL;
    public static final int IF_ACMPEQ;
    public static final int IF_ACMPNE;
    public static final int IF_ICMPEQ;
    public static final int IF_ICMPGE;
    public static final int IF_ICMPGT;
    public static final int IF_ICMPLE;
    public static final int IF_ICMPLT;
    public static final int IF_ICMPNE;
    public static final int IINC;
    public static final int ILOAD;
    public static final int ILOAD_0;
    public static final int ILOAD_1;
    public static final int ILOAD_2;
    public static final int ILOAD_3;
    public static final int IMUL;
    public static final int INEG;
    public static final int INSTANCEOF;
    public static final int INVOKEDYNAMIC;
    public static final int INVOKEINTERFACE;
    public static final int INVOKESPECIAL;
    public static final int INVOKESTATIC;
    public static final int INVOKEVIRTUAL;
    public static final int IOR;
    public static final int IREM;
    public static final int IRETURN;
    public static final int ISHL;
    public static final int ISHR;
    public static final int ISTORE;
    public static final int ISTORE_0;
    public static final int ISTORE_1;
    public static final int ISTORE_2;
    public static final int ISTORE_3;
    public static final int ISUB;
    public static final int IUSHR;
    public static final int IXOR;
    public static final int JSR;
    public static final int JSR_W;
    public static final int L2D;
    public static final int L2F;
    public static final int L2I;
    public static final int LADD;
    public static final int LALOAD;
    public static final int LAND;
    public static final int LASTORE;
    public static final int LCMP;
    public static final int LCONST_0;
    public static final int LCONST_1;
    public static final int LDC;
    public static final int LDC2_W;
    public static final int LDC_W;
    public static final int LDIV;
    public static final int LLOAD;
    public static final int LLOAD_0;
    public static final int LLOAD_1;
    public static final int LLOAD_2;
    public static final int LLOAD_3;
    public static final int LMUL;
    public static final int LNEG;
    public static final int LOOKUPSWITCH;
    public static final int LOR;
    public static final int LREM;
    public static final int LRETURN;
    public static final int LSHL;
    public static final int LSHR;
    public static final int LSTORE;
    public static final int LSTORE_0;
    public static final int LSTORE_1;
    public static final int LSTORE_2;
    public static final int LSTORE_3;
    public static final int LSUB;
    public static final int LUSHR;
    public static final int LXOR;
    public static final int MONITORENTER;
    public static final int MONITOREXIT;
    public static final int MULTIANEWARRAY;
    public static final int NEW;
    public static final int NEWARRAY;
    public static final int NOP;
    public static final int POP;
    public static final int POP2;
    public static final int PUTFIELD;
    public static final int PUTSTATIC;
    public static final int RET;
    public static final int RETURN;
    public static final int SALOAD;
    public static final int SASTORE;
    public static final int SIPUSH;
    public static final int SWAP;
    public static final int TABLESWITCH;
    public static final int WIDE;
    public static final int T_BOOLEAN;
    public static final int T_CHAR;
    public static final int T_FLOAT;
    public static final int T_DOUBLE;
    public static final int T_BYTE;
    public static final int T_SHORT;
    public static final int T_INT;
    public static final int T_LONG;
    public static final int[] STACK_GROW;

    static void <clinit>()
    {
        int[] $r0;

        <javassist.bytecode.Opcode: int T_LONG> = 11;

        <javassist.bytecode.Opcode: int T_INT> = 10;

        <javassist.bytecode.Opcode: int T_SHORT> = 9;

        <javassist.bytecode.Opcode: int T_BYTE> = 8;

        <javassist.bytecode.Opcode: int T_DOUBLE> = 7;

        <javassist.bytecode.Opcode: int T_FLOAT> = 6;

        <javassist.bytecode.Opcode: int T_CHAR> = 5;

        <javassist.bytecode.Opcode: int T_BOOLEAN> = 4;

        <javassist.bytecode.Opcode: int WIDE> = 196;

        <javassist.bytecode.Opcode: int TABLESWITCH> = 170;

        <javassist.bytecode.Opcode: int SWAP> = 95;

        <javassist.bytecode.Opcode: int SIPUSH> = 17;

        <javassist.bytecode.Opcode: int SASTORE> = 86;

        <javassist.bytecode.Opcode: int SALOAD> = 53;

        <javassist.bytecode.Opcode: int RETURN> = 177;

        <javassist.bytecode.Opcode: int RET> = 169;

        <javassist.bytecode.Opcode: int PUTSTATIC> = 179;

        <javassist.bytecode.Opcode: int PUTFIELD> = 181;

        <javassist.bytecode.Opcode: int POP2> = 88;

        <javassist.bytecode.Opcode: int POP> = 87;

        <javassist.bytecode.Opcode: int NOP> = 0;

        <javassist.bytecode.Opcode: int NEWARRAY> = 188;

        <javassist.bytecode.Opcode: int NEW> = 187;

        <javassist.bytecode.Opcode: int MULTIANEWARRAY> = 197;

        <javassist.bytecode.Opcode: int MONITOREXIT> = 195;

        <javassist.bytecode.Opcode: int MONITORENTER> = 194;

        <javassist.bytecode.Opcode: int LXOR> = 131;

        <javassist.bytecode.Opcode: int LUSHR> = 125;

        <javassist.bytecode.Opcode: int LSUB> = 101;

        <javassist.bytecode.Opcode: int LSTORE_3> = 66;

        <javassist.bytecode.Opcode: int LSTORE_2> = 65;

        <javassist.bytecode.Opcode: int LSTORE_1> = 64;

        <javassist.bytecode.Opcode: int LSTORE_0> = 63;

        <javassist.bytecode.Opcode: int LSTORE> = 55;

        <javassist.bytecode.Opcode: int LSHR> = 123;

        <javassist.bytecode.Opcode: int LSHL> = 121;

        <javassist.bytecode.Opcode: int LRETURN> = 173;

        <javassist.bytecode.Opcode: int LREM> = 113;

        <javassist.bytecode.Opcode: int LOR> = 129;

        <javassist.bytecode.Opcode: int LOOKUPSWITCH> = 171;

        <javassist.bytecode.Opcode: int LNEG> = 117;

        <javassist.bytecode.Opcode: int LMUL> = 105;

        <javassist.bytecode.Opcode: int LLOAD_3> = 33;

        <javassist.bytecode.Opcode: int LLOAD_2> = 32;

        <javassist.bytecode.Opcode: int LLOAD_1> = 31;

        <javassist.bytecode.Opcode: int LLOAD_0> = 30;

        <javassist.bytecode.Opcode: int LLOAD> = 22;

        <javassist.bytecode.Opcode: int LDIV> = 109;

        <javassist.bytecode.Opcode: int LDC_W> = 19;

        <javassist.bytecode.Opcode: int LDC2_W> = 20;

        <javassist.bytecode.Opcode: int LDC> = 18;

        <javassist.bytecode.Opcode: int LCONST_1> = 10;

        <javassist.bytecode.Opcode: int LCONST_0> = 9;

        <javassist.bytecode.Opcode: int LCMP> = 148;

        <javassist.bytecode.Opcode: int LASTORE> = 80;

        <javassist.bytecode.Opcode: int LAND> = 127;

        <javassist.bytecode.Opcode: int LALOAD> = 47;

        <javassist.bytecode.Opcode: int LADD> = 97;

        <javassist.bytecode.Opcode: int L2I> = 136;

        <javassist.bytecode.Opcode: int L2F> = 137;

        <javassist.bytecode.Opcode: int L2D> = 138;

        <javassist.bytecode.Opcode: int JSR_W> = 201;

        <javassist.bytecode.Opcode: int JSR> = 168;

        <javassist.bytecode.Opcode: int IXOR> = 130;

        <javassist.bytecode.Opcode: int IUSHR> = 124;

        <javassist.bytecode.Opcode: int ISUB> = 100;

        <javassist.bytecode.Opcode: int ISTORE_3> = 62;

        <javassist.bytecode.Opcode: int ISTORE_2> = 61;

        <javassist.bytecode.Opcode: int ISTORE_1> = 60;

        <javassist.bytecode.Opcode: int ISTORE_0> = 59;

        <javassist.bytecode.Opcode: int ISTORE> = 54;

        <javassist.bytecode.Opcode: int ISHR> = 122;

        <javassist.bytecode.Opcode: int ISHL> = 120;

        <javassist.bytecode.Opcode: int IRETURN> = 172;

        <javassist.bytecode.Opcode: int IREM> = 112;

        <javassist.bytecode.Opcode: int IOR> = 128;

        <javassist.bytecode.Opcode: int INVOKEVIRTUAL> = 182;

        <javassist.bytecode.Opcode: int INVOKESTATIC> = 184;

        <javassist.bytecode.Opcode: int INVOKESPECIAL> = 183;

        <javassist.bytecode.Opcode: int INVOKEINTERFACE> = 185;

        <javassist.bytecode.Opcode: int INVOKEDYNAMIC> = 186;

        <javassist.bytecode.Opcode: int INSTANCEOF> = 193;

        <javassist.bytecode.Opcode: int INEG> = 116;

        <javassist.bytecode.Opcode: int IMUL> = 104;

        <javassist.bytecode.Opcode: int ILOAD_3> = 29;

        <javassist.bytecode.Opcode: int ILOAD_2> = 28;

        <javassist.bytecode.Opcode: int ILOAD_1> = 27;

        <javassist.bytecode.Opcode: int ILOAD_0> = 26;

        <javassist.bytecode.Opcode: int ILOAD> = 21;

        <javassist.bytecode.Opcode: int IINC> = 132;

        <javassist.bytecode.Opcode: int IF_ICMPNE> = 160;

        <javassist.bytecode.Opcode: int IF_ICMPLT> = 161;

        <javassist.bytecode.Opcode: int IF_ICMPLE> = 164;

        <javassist.bytecode.Opcode: int IF_ICMPGT> = 163;

        <javassist.bytecode.Opcode: int IF_ICMPGE> = 162;

        <javassist.bytecode.Opcode: int IF_ICMPEQ> = 159;

        <javassist.bytecode.Opcode: int IF_ACMPNE> = 166;

        <javassist.bytecode.Opcode: int IF_ACMPEQ> = 165;

        <javassist.bytecode.Opcode: int IFNULL> = 198;

        <javassist.bytecode.Opcode: int IFNONNULL> = 199;

        <javassist.bytecode.Opcode: int IFNE> = 154;

        <javassist.bytecode.Opcode: int IFLT> = 155;

        <javassist.bytecode.Opcode: int IFLE> = 158;

        <javassist.bytecode.Opcode: int IFGT> = 157;

        <javassist.bytecode.Opcode: int IFGE> = 156;

        <javassist.bytecode.Opcode: int IFEQ> = 153;

        <javassist.bytecode.Opcode: int IDIV> = 108;

        <javassist.bytecode.Opcode: int ICONST_M1> = 2;

        <javassist.bytecode.Opcode: int ICONST_5> = 8;

        <javassist.bytecode.Opcode: int ICONST_4> = 7;

        <javassist.bytecode.Opcode: int ICONST_3> = 6;

        <javassist.bytecode.Opcode: int ICONST_2> = 5;

        <javassist.bytecode.Opcode: int ICONST_1> = 4;

        <javassist.bytecode.Opcode: int ICONST_0> = 3;

        <javassist.bytecode.Opcode: int IASTORE> = 79;

        <javassist.bytecode.Opcode: int IAND> = 126;

        <javassist.bytecode.Opcode: int IALOAD> = 46;

        <javassist.bytecode.Opcode: int IADD> = 96;

        <javassist.bytecode.Opcode: int I2S> = 147;

        <javassist.bytecode.Opcode: int I2L> = 133;

        <javassist.bytecode.Opcode: int I2F> = 134;

        <javassist.bytecode.Opcode: int I2D> = 135;

        <javassist.bytecode.Opcode: int I2C> = 146;

        <javassist.bytecode.Opcode: int I2B> = 145;

        <javassist.bytecode.Opcode: int GOTO_W> = 200;

        <javassist.bytecode.Opcode: int GOTO> = 167;

        <javassist.bytecode.Opcode: int GETSTATIC> = 178;

        <javassist.bytecode.Opcode: int GETFIELD> = 180;

        <javassist.bytecode.Opcode: int FSUB> = 102;

        <javassist.bytecode.Opcode: int FSTORE_3> = 70;

        <javassist.bytecode.Opcode: int FSTORE_2> = 69;

        <javassist.bytecode.Opcode: int FSTORE_1> = 68;

        <javassist.bytecode.Opcode: int FSTORE_0> = 67;

        <javassist.bytecode.Opcode: int FSTORE> = 56;

        <javassist.bytecode.Opcode: int FRETURN> = 174;

        <javassist.bytecode.Opcode: int FREM> = 114;

        <javassist.bytecode.Opcode: int FNEG> = 118;

        <javassist.bytecode.Opcode: int FMUL> = 106;

        <javassist.bytecode.Opcode: int FLOAD_3> = 37;

        <javassist.bytecode.Opcode: int FLOAD_2> = 36;

        <javassist.bytecode.Opcode: int FLOAD_1> = 35;

        <javassist.bytecode.Opcode: int FLOAD_0> = 34;

        <javassist.bytecode.Opcode: int FLOAD> = 23;

        <javassist.bytecode.Opcode: int FDIV> = 110;

        <javassist.bytecode.Opcode: int FCONST_2> = 13;

        <javassist.bytecode.Opcode: int FCONST_1> = 12;

        <javassist.bytecode.Opcode: int FCONST_0> = 11;

        <javassist.bytecode.Opcode: int FCMPL> = 149;

        <javassist.bytecode.Opcode: int FCMPG> = 150;

        <javassist.bytecode.Opcode: int FASTORE> = 81;

        <javassist.bytecode.Opcode: int FALOAD> = 48;

        <javassist.bytecode.Opcode: int FADD> = 98;

        <javassist.bytecode.Opcode: int F2L> = 140;

        <javassist.bytecode.Opcode: int F2I> = 139;

        <javassist.bytecode.Opcode: int F2D> = 141;

        <javassist.bytecode.Opcode: int DUP_X2> = 91;

        <javassist.bytecode.Opcode: int DUP_X1> = 90;

        <javassist.bytecode.Opcode: int DUP2_X2> = 94;

        <javassist.bytecode.Opcode: int DUP2_X1> = 93;

        <javassist.bytecode.Opcode: int DUP2> = 92;

        <javassist.bytecode.Opcode: int DUP> = 89;

        <javassist.bytecode.Opcode: int DSUB> = 103;

        <javassist.bytecode.Opcode: int DSTORE_3> = 74;

        <javassist.bytecode.Opcode: int DSTORE_2> = 73;

        <javassist.bytecode.Opcode: int DSTORE_1> = 72;

        <javassist.bytecode.Opcode: int DSTORE_0> = 71;

        <javassist.bytecode.Opcode: int DSTORE> = 57;

        <javassist.bytecode.Opcode: int DRETURN> = 175;

        <javassist.bytecode.Opcode: int DREM> = 115;

        <javassist.bytecode.Opcode: int DNEG> = 119;

        <javassist.bytecode.Opcode: int DMUL> = 107;

        <javassist.bytecode.Opcode: int DLOAD_3> = 41;

        <javassist.bytecode.Opcode: int DLOAD_2> = 40;

        <javassist.bytecode.Opcode: int DLOAD_1> = 39;

        <javassist.bytecode.Opcode: int DLOAD_0> = 38;

        <javassist.bytecode.Opcode: int DLOAD> = 24;

        <javassist.bytecode.Opcode: int DDIV> = 111;

        <javassist.bytecode.Opcode: int DCONST_1> = 15;

        <javassist.bytecode.Opcode: int DCONST_0> = 14;

        <javassist.bytecode.Opcode: int DCMPL> = 151;

        <javassist.bytecode.Opcode: int DCMPG> = 152;

        <javassist.bytecode.Opcode: int DASTORE> = 82;

        <javassist.bytecode.Opcode: int DALOAD> = 49;

        <javassist.bytecode.Opcode: int DADD> = 99;

        <javassist.bytecode.Opcode: int D2L> = 143;

        <javassist.bytecode.Opcode: int D2I> = 142;

        <javassist.bytecode.Opcode: int D2F> = 144;

        <javassist.bytecode.Opcode: int CHECKCAST> = 192;

        <javassist.bytecode.Opcode: int CASTORE> = 85;

        <javassist.bytecode.Opcode: int CALOAD> = 52;

        <javassist.bytecode.Opcode: int BIPUSH> = 16;

        <javassist.bytecode.Opcode: int BASTORE> = 84;

        <javassist.bytecode.Opcode: int BALOAD> = 51;

        <javassist.bytecode.Opcode: int ATHROW> = 191;

        <javassist.bytecode.Opcode: int ASTORE_3> = 78;

        <javassist.bytecode.Opcode: int ASTORE_2> = 77;

        <javassist.bytecode.Opcode: int ASTORE_1> = 76;

        <javassist.bytecode.Opcode: int ASTORE_0> = 75;

        <javassist.bytecode.Opcode: int ASTORE> = 58;

        <javassist.bytecode.Opcode: int ARRAYLENGTH> = 190;

        <javassist.bytecode.Opcode: int ARETURN> = 176;

        <javassist.bytecode.Opcode: int ANEWARRAY> = 189;

        <javassist.bytecode.Opcode: int ALOAD_3> = 45;

        <javassist.bytecode.Opcode: int ALOAD_2> = 44;

        <javassist.bytecode.Opcode: int ALOAD_1> = 43;

        <javassist.bytecode.Opcode: int ALOAD_0> = 42;

        <javassist.bytecode.Opcode: int ALOAD> = 25;

        <javassist.bytecode.Opcode: int ACONST_NULL> = 1;

        <javassist.bytecode.Opcode: int AASTORE> = 83;

        <javassist.bytecode.Opcode: int AALOAD> = 50;

        $r0 = newarray (int)[202];

        $r0[0] = 0;

        $r0[1] = 1;

        $r0[2] = 1;

        $r0[3] = 1;

        $r0[4] = 1;

        $r0[5] = 1;

        $r0[6] = 1;

        $r0[7] = 1;

        $r0[8] = 1;

        $r0[9] = 2;

        $r0[10] = 2;

        $r0[11] = 1;

        $r0[12] = 1;

        $r0[13] = 1;

        $r0[14] = 2;

        $r0[15] = 2;

        $r0[16] = 1;

        $r0[17] = 1;

        $r0[18] = 1;

        $r0[19] = 1;

        $r0[20] = 2;

        $r0[21] = 1;

        $r0[22] = 2;

        $r0[23] = 1;

        $r0[24] = 2;

        $r0[25] = 1;

        $r0[26] = 1;

        $r0[27] = 1;

        $r0[28] = 1;

        $r0[29] = 1;

        $r0[30] = 2;

        $r0[31] = 2;

        $r0[32] = 2;

        $r0[33] = 2;

        $r0[34] = 1;

        $r0[35] = 1;

        $r0[36] = 1;

        $r0[37] = 1;

        $r0[38] = 2;

        $r0[39] = 2;

        $r0[40] = 2;

        $r0[41] = 2;

        $r0[42] = 1;

        $r0[43] = 1;

        $r0[44] = 1;

        $r0[45] = 1;

        $r0[46] = -1;

        $r0[47] = 0;

        $r0[48] = -1;

        $r0[49] = 0;

        $r0[50] = -1;

        $r0[51] = -1;

        $r0[52] = -1;

        $r0[53] = -1;

        $r0[54] = -1;

        $r0[55] = -2;

        $r0[56] = -1;

        $r0[57] = -2;

        $r0[58] = -1;

        $r0[59] = -1;

        $r0[60] = -1;

        $r0[61] = -1;

        $r0[62] = -1;

        $r0[63] = -2;

        $r0[64] = -2;

        $r0[65] = -2;

        $r0[66] = -2;

        $r0[67] = -1;

        $r0[68] = -1;

        $r0[69] = -1;

        $r0[70] = -1;

        $r0[71] = -2;

        $r0[72] = -2;

        $r0[73] = -2;

        $r0[74] = -2;

        $r0[75] = -1;

        $r0[76] = -1;

        $r0[77] = -1;

        $r0[78] = -1;

        $r0[79] = -3;

        $r0[80] = -4;

        $r0[81] = -3;

        $r0[82] = -4;

        $r0[83] = -3;

        $r0[84] = -3;

        $r0[85] = -3;

        $r0[86] = -3;

        $r0[87] = -1;

        $r0[88] = -2;

        $r0[89] = 1;

        $r0[90] = 1;

        $r0[91] = 1;

        $r0[92] = 2;

        $r0[93] = 2;

        $r0[94] = 2;

        $r0[95] = 0;

        $r0[96] = -1;

        $r0[97] = -2;

        $r0[98] = -1;

        $r0[99] = -2;

        $r0[100] = -1;

        $r0[101] = -2;

        $r0[102] = -1;

        $r0[103] = -2;

        $r0[104] = -1;

        $r0[105] = -2;

        $r0[106] = -1;

        $r0[107] = -2;

        $r0[108] = -1;

        $r0[109] = -2;

        $r0[110] = -1;

        $r0[111] = -2;

        $r0[112] = -1;

        $r0[113] = -2;

        $r0[114] = -1;

        $r0[115] = -2;

        $r0[116] = 0;

        $r0[117] = 0;

        $r0[118] = 0;

        $r0[119] = 0;

        $r0[120] = -1;

        $r0[121] = -1;

        $r0[122] = -1;

        $r0[123] = -1;

        $r0[124] = -1;

        $r0[125] = -1;

        $r0[126] = -1;

        $r0[127] = -2;

        $r0[128] = -1;

        $r0[129] = -2;

        $r0[130] = -1;

        $r0[131] = -2;

        $r0[132] = 0;

        $r0[133] = 1;

        $r0[134] = 0;

        $r0[135] = 1;

        $r0[136] = -1;

        $r0[137] = -1;

        $r0[138] = 0;

        $r0[139] = 0;

        $r0[140] = 1;

        $r0[141] = 1;

        $r0[142] = -1;

        $r0[143] = 0;

        $r0[144] = -1;

        $r0[145] = 0;

        $r0[146] = 0;

        $r0[147] = 0;

        $r0[148] = -3;

        $r0[149] = -1;

        $r0[150] = -1;

        $r0[151] = -3;

        $r0[152] = -3;

        $r0[153] = -1;

        $r0[154] = -1;

        $r0[155] = -1;

        $r0[156] = -1;

        $r0[157] = -1;

        $r0[158] = -1;

        $r0[159] = -2;

        $r0[160] = -2;

        $r0[161] = -2;

        $r0[162] = -2;

        $r0[163] = -2;

        $r0[164] = -2;

        $r0[165] = -2;

        $r0[166] = -2;

        $r0[167] = 0;

        $r0[168] = 1;

        $r0[169] = 0;

        $r0[170] = -1;

        $r0[171] = -1;

        $r0[172] = -1;

        $r0[173] = -2;

        $r0[174] = -1;

        $r0[175] = -2;

        $r0[176] = -1;

        $r0[177] = 0;

        $r0[178] = 0;

        $r0[179] = 0;

        $r0[180] = 0;

        $r0[181] = 0;

        $r0[182] = 0;

        $r0[183] = 0;

        $r0[184] = 0;

        $r0[185] = 0;

        $r0[186] = 0;

        $r0[187] = 1;

        $r0[188] = 0;

        $r0[189] = 0;

        $r0[190] = 0;

        $r0[191] = -1;

        $r0[192] = 0;

        $r0[193] = 0;

        $r0[194] = -1;

        $r0[195] = -1;

        $r0[196] = 0;

        $r0[197] = 0;

        $r0[198] = -1;

        $r0[199] = -1;

        $r0[200] = 0;

        $r0[201] = 1;

        <javassist.bytecode.Opcode: int[] STACK_GROW> = $r0;

        return;
    }
}
